<annotation>
	<folder>train</folder>
	<filename>IMG_9874.JPG</filename>
	<path>C:\Users\sasimo\Desktop\kakipi08\data\images\train\IMG_9874.JPG</path>
	<source>
		<database>Unknown</database>
	</source>
	<size>
		<width>4032</width>
		<height>3024</height>
		<depth>3</depth>
	</size>
	<segmented>0</segmented>
	<object>
		<name>peanut</name>
		<pose>Unspecified</pose>
		<truncated>0</truncated>
		<difficult>0</difficult>
		<bndbox>
			<xmin>1042</xmin>
			<ymin>748</ymin>
			<xmax>1346</xmax>
			<ymax>1132</ymax>
		</bndbox>
	</object>
	<object>
		<name>peanut</name>
		<pose>Unspecified</pose>
		<truncated>0</truncated>
		<difficult>0</difficult>
		<bndbox>
			<xmin>2142</xmin>
			<ymin>548</ymin>
			<xmax>2570</xmax>
			<ymax>820</ymax>
		</bndbox>
	</object>
	<object>
		<name>peanut</name>
		<pose>Unspecified</pose>
		<truncated>0</truncated>
		<difficult>0</difficult>
		<bndbox>
			<xmin>2938</xmin>
			<ymin>1424</ymin>
			<xmax>3242</xmax>
			<ymax>1836</ymax>
		</bndbox>
	</object>
	<object>
		<name>peanut</name>
		<pose>Unspecified</pose>
		<truncated>0</truncated>
		<difficult>0</difficult>
		<bndbox>
			<xmin>2562</xmin>
			<ymin>2204</ymin>
			<xmax>3102</xmax>
			<ymax>2500</ymax>
		</bndbox>
	</object>
	<object>
		<name>peanut</name>
		<pose>Unspecified</pose>
		<truncated>0</truncated>
		<difficult>0</difficult>
		<bndbox>
			<xmin>1998</xmin>
			<ymin>2436</ymin>
			<xmax>2370</xmax>
			<ymax>2796</ymax>
		</bndbox>
	</object>
	<object>
		<name>kaki</name>
		<pose>Unspecified</pose>
		<truncated>0</truncated>
		<difficult>0</difficult>
		<bndbox>
			<xmin>2546</xmin>
			<ymin>424</ymin>
			<xmax>3114</xmax>
			<ymax>948</ymax>
		</bndbox>
	</object>
	<object>
		<name>kaki</name>
		<pose>Unspecified</pose>
		<truncated>0</truncated>
		<difficult>0</difficult>
		<bndbox>
			<xmin>2562</xmin>
			<ymin>760</ymin>
			<xmax>2838</xmax>
			<ymax>1376</ymax>
		</bndbox>
	</object>
	<object>
		<name>kaki</name>
		<pose>Unspecified</pose>
		<truncated>0</truncated>
		<difficult>0</difficult>
		<bndbox>
			<xmin>1898</xmin>
			<ymin>752</ymin>
			<xmax>2162</xmax>
			<ymax>1420</ymax>
		</bndbox>
	</object>
	<object>
		<name>kaki</name>
		<pose>Unspecified</pose>
		<truncated>0</truncated>
		<difficult>0</difficult>
		<bndbox>
			<xmin>3214</xmin>
			<ymin>1348</ymin>
			<xmax>3878</xmax>
			<ymax>1720</ymax>
		</bndbox>
	</object>
	<object>
		<name>kaki</name>
		<pose>Unspecified</pose>
		<truncated>0</truncated>
		<difficult>0</difficult>
		<bndbox>
			<xmin>1314</xmin>
			<ymin>1220</ymin>
			<xmax>1826</xmax>
			<ymax>1748</ymax>
		</bndbox>
	</object>
	<object>
		<name>kaki</name>
		<pose>Unspecified</pose>
		<truncated>0</truncated>
		<difficult>0</difficult>
		<bndbox>
			<xmin>2142</xmin>
			<ymin>1220</ymin>
			<xmax>2354</xmax>
			<ymax>1888</ymax>
		</bndbox>
	</object>
	<object>
		<name>kaki</name>
		<pose>Unspecified</pose>
		<truncated>0</truncated>
		<difficult>0</difficult>
		<bndbox>
			<xmin>2350</xmin>
			<ymin>1584</ymin>
			<xmax>2970</xmax>
			<ymax>2008</ymax>
		</bndbox>
	</object>
	<object>
		<name>kaki</name>
		<pose>Unspecified</pose>
		<truncated>0</truncated>
		<difficult>0</difficult>
		<bndbox>
			<xmin>578</xmin>
			<ymin>1608</ymin>
			<xmax>1214</xmax>
			<ymax>1936</ymax>
		</bndbox>
	</object>
	<object>
		<name>kaki</name>
		<pose>Unspecified</pose>
		<truncated>0</truncated>
		<difficult>0</difficult>
		<bndbox>
			<xmin>1914</xmin>
			<ymin>1624</ymin>
			<xmax>2226</xmax>
			<ymax>2248</ymax>
		</bndbox>
	</object>
</annotation>
